orm.py
sqlite_orm-0.0.2b0.dist-info/DESCRIPTION.rst
sqlite_orm-0.0.2b0.dist-info/METADATA
sqlite_orm-0.0.2b0.dist-info/RECORD
sqlite_orm-0.0.2b0.dist-info/WHEEL
sqlite_orm-0.0.2b0.dist-info/metadata.json
sqlite_orm-0.0.2b0.dist-info/top_level.txt
